agentscript_pyo3-0.1.1.dist-info/METADATA
agentscript_pyo3-0.1.1.dist-info/WHEEL
agentscript_pyo3-0.1.1.dist-info/license_files/LICENSE
agentscript_pyo3/__init__.py
agentscript_pyo3/agentscript_pyo3.cpython-310-darwin.so
agentscript_pyo3-0.1.1.dist-info/RECORD
